<?xml version="1.0" encoding="utf-8"?>
<ArrayOfVozac xmlns:xsi="http://www.w3.org/2001/XMLSchema-instance" xmlns:xsd="http://www.w3.org/2001/XMLSchema">
  <Vozac>
    <KorisnickoIme>suza</KorisnickoIme>
    <Lozinka>suza</Lozinka>
    <Ime>Suzana</Ime>
    <Prezime>Jovic</Prezime>
    <Pol>Zensko</Pol>
    <JMBG>1234567890123</JMBG>
    <KontaktTelefon>04823875</KontaktTelefon>
    <Email>suza@suza</Email>
    <Uloga>Vozac</Uloga>
    <KorisnikVoznje />
    <Lok>
      <Xkoordinate>-66.375004</Xkoordinate>
      <Ykoordinate>-1.757539</Ykoordinate>
      <Adr>
        <FormatAdrese>Japurá, Microrregião de Japurá, Mesorregião Norte Amazonense, AM, Região Norte, Brasil</FormatAdrese>
      </Adr>
    </Lok>
    <Auto>
      <UsernameVozaca>suza</UsernameVozaca>
      <GodisteAutomobila>1397</GodisteAutomobila>
      <BrojRegistarskeOzn>ns201</BrojRegistarskeOzn>
      <BrojTaksiVozila>1</BrojTaksiVozila>
      <TA>putnicki</TA>
    </Auto>
    <Zauzet>true</Zauzet>
    <Blokiran>false</Blokiran>
  </Vozac>
  <Vozac>
    <KorisnickoIme>tami123</KorisnickoIme>
    <Lozinka>tami</Lozinka>
    <Ime>Tamara</Ime>
    <Prezime>Gengo</Prezime>
    <Pol>Zensko</Pol>
    <JMBG>1234567890123</JMBG>
    <KontaktTelefon>04823875</KontaktTelefon>
    <Email>gica@tami</Email>
    <Uloga>Vozac</Uloga>
    <KorisnikVoznje />
    <Lok>
      <Xkoordinate>81.492194</Xkoordinate>
      <Ykoordinate>54.977606</Ykoordinate>
      <Adr>
        <FormatAdrese>Осиновский сельсовет, Чулымский район, Новосибирская область, СФО, РФ</FormatAdrese>
      </Adr>
    </Lok>
    <Auto>
      <UsernameVozaca>tami123</UsernameVozaca>
      <GodisteAutomobila>1920</GodisteAutomobila>
      <BrojRegistarskeOzn>nss</BrojRegistarskeOzn>
      <BrojTaksiVozila>2</BrojTaksiVozila>
      <TA>kombi</TA>
    </Auto>
    <Zauzet>false</Zauzet>
    <Blokiran>false</Blokiran>
  </Vozac>
</ArrayOfVozac>